LICENSE
tradernet_api/__init__.py
tradernet_api/api.py
tradernet_api/client.py
tradernet_api/commands/__init__.py
tradernet_api/commands/delete_order.py
tradernet_api/commands/get_orders.py
tradernet_api/commands/get_ticker_info.py
tradernet_api/commands/send_order.py
tradernet_api/commands/set_stop_order.py
tradernet_api/const.py
tradernet_api/models/__init__.py
tradernet_api/models/command_model.py
tradernet_api/models/request_model.py
tradernet_api/session.py
tradernet_api-1.1.2.dist-info/LICENSE
tradernet_api-1.1.2.dist-info/METADATA
tradernet_api-1.1.2.dist-info/WHEEL
tradernet_api-1.1.2.dist-info/RECORD
