Metadata-Version: 2.1
Name: tradernet-api
Version: 1.1.2
Summary: Public API client for working with the Tradernet platform.
License: MIT
Author: Artur Kutsevol
Author-email: arthur.kutsevol@gmail.com
Requires-Python: >=3.10,<4.0
Classifier: License :: OSI Approved :: MIT License
Classifier: Programming Language :: Python :: 3
Classifier: Programming Language :: Python :: 3.10
Classifier: Programming Language :: Python :: 3.11
Requires-Dist: pydantic (>=1.9.1,<2.0.0)
Requires-Dist: requests (>=2.27.1,<3.0.0)
